{
    "compile_time": 233.623,
    "total_time": 327.133,
    "sat_is_instantiated_var": 2.137087,
    "sat_is_irrelevant_var": 0.017348,
    "sat_var_count": 0.0,
    "sat_var2pliteral": 6.578791,
    "sat_var2nliteral": 6.603215,
    "sat_is_implied_literal": 12.98009,
    "sat_literal_weight": 0.0,
    "sat_decide_literal": 1.541773,
    "sat_undo_decide_literal": 0.839409,
    "sat_is_subsumed_clause": 79.531469,
    "sat_clause_count": 0.0,
    "sat_learned_clause_count": 0.0,
    "sat_assert_clause": 0.479925,
    "sat_state_new": 0.017417,
    "sat_state_free": 0.007067,
    "sat_assert_unit_clauses": 1.2e-05,
    "sat_undo_assert_unit_clauses": 4e-06,
    "sat_at_assertion_level": 0.013714,
    "nnf_manager_new": 6.2e-05,
    "nnf_manager_free": 0.00093,
    "nnf_manager_memory": 1e-06,
    "nnf_literal2node": 0.648346,
    "nnf_conjoin": 0.776869,
    "nnf_disjoin": 0.00624,
    "nnf_count_nodes": 0.0,
    "nnf_manager_set_root": 1e-06,
    "nnf_manager_get_root": 0.0,
    "nnf_manager_extract_nnf": 0.0,
    "nnf_manager_save_to_file": 0.031934,
    "nnf_load_from_file": 0.0,
    "nnf_free": 0.0,
    "nnf_node_count": 0.0,
    "nnf_edge_count": 0.0,
    "nnf_count_models": 0.0,
    "nnf_entails_cnf": 0.0,
    "nnf_decomposable": 0.0,
    "vtree_manager_new": 93.446897,
    "vtree_manager_free": 0.016072,
    "vtree_save": 0.0,
    "vtree_save_as_dot": 0.0,
    "vtree_print_widths": 7.4e-05,
    "vtree_is_leaf": 0.903799,
    "vtree_is_shannon_node": 2.354263,
    "vtree_shannon_var": 2.128762
}